kaizo/__init__.py
kaizo/parser.py
kaizo/plugins/__init__.py
kaizo/plugins/core.py
kaizo/utils/__init__.py
kaizo/utils/cache.py
kaizo/utils/common.py
kaizo/utils/entry.py
kaizo/utils/exception.py
kaizo/utils/fn.py
kaizo/utils/module.py
kaizo/utils/storage.py
kaizo-1.5.5.dist-info/licenses/LICENSE
kaizo-1.5.5.dist-info/METADATA
kaizo-1.5.5.dist-info/WHEEL
kaizo-1.5.5.dist-info/top_level.txt
kaizo-1.5.5.dist-info/RECORD
