Metadata-Version: 2.4
Name: kaizo
Version: 1.5.5
Summary: declarative YAML-based configuration parser
Author-email: Mohammad Ghazanfari <mgh.5225@gmail.com>
Project-URL: Homepage, https://github.com/NaughtFound/kaizo
Project-URL: Source, https://github.com/NaughtFound/kaizo
Project-URL: Issues, https://github.com/NaughtFound/kaizo/issues
Project-URL: Changelog, https://github.com/NaughtFound/kaizo/blob/main/CHANGELOG.md
Project-URL: Documentation, https://NaughtFound.github.io/kaizo
Classifier: Programming Language :: Python :: 3
Classifier: Operating System :: OS Independent
Requires-Python: >=3.10
License-File: LICENSE
Requires-Dist: pyyaml>=6.0.3
Requires-Dist: typing-extensions>=4.15.0
Provides-Extra: hf
Requires-Dist: kaizo-hf; extra == "hf"
Dynamic: license-file
